ackc/__init__.py
ackc/base.py
ackc/env.py
ackc/exceptions.py
ackc/keycloak.py
ackc/management.py
ackc/tokens.py
ackc/api/__init__.py
ackc/api/attack_detection.py
ackc/api/authentication.py
ackc/api/authorization.py
ackc/api/base.py
ackc/api/client_attribute_certificate.py
ackc/api/client_initial_access.py
ackc/api/client_registration_policy.py
ackc/api/client_role_mappings.py
ackc/api/client_scopes.py
ackc/api/clients.py
ackc/api/components.py
ackc/api/events.py
ackc/api/groups.py
ackc/api/identity_providers.py
ackc/api/keys.py
ackc/api/organizations.py
ackc/api/protocol_mappers.py
ackc/api/realms.py
ackc/api/role_mapper.py
ackc/api/roles.py
ackc/api/roles_by_id.py
ackc/api/scope_mappings.py
ackc/api/sessions.py
ackc/api/users.py
ackc/generated/.gitignore
ackc/generated/__init__.py
ackc/generated/client.py
ackc/generated/errors.py
ackc/generated/py.typed
ackc/generated/types.py
ackc/generated/api/__init__.py
ackc/generated/api/attack_detection/__init__.py
ackc/generated/api/attack_detection/delete_admin_realms_realm_attack_detection_brute_force_users.py
ackc/generated/api/attack_detection/delete_admin_realms_realm_attack_detection_brute_force_users_user_id.py
ackc/generated/api/attack_detection/get_admin_realms_realm_attack_detection_brute_force_users_user_id.py
ackc/generated/api/authentication_management/__init__.py
ackc/generated/api/authentication_management/delete_admin_realms_realm_authentication_config_id.py
ackc/generated/api/authentication_management/delete_admin_realms_realm_authentication_executions_execution_id.py
ackc/generated/api/authentication_management/delete_admin_realms_realm_authentication_flows_id.py
ackc/generated/api/authentication_management/delete_admin_realms_realm_authentication_required_actions_alias.py
ackc/generated/api/authentication_management/delete_admin_realms_realm_authentication_required_actions_alias_config.py
ackc/generated/api/authentication_management/get_admin_realms_realm_authentication_authenticator_providers.py
ackc-1.0.0.dist-info/METADATA
ackc-1.0.0.dist-info/WHEEL
ackc-1.0.0.dist-info/entry_points.txt
ackc-1.0.0.dist-info/licenses/license.md
ackc-1.0.0.dist-info/RECORD
