Metadata-Version: 2.4
Name: ackc
Version: 1.0.0
Summary: API Client for Keycloak
Project-URL: Homepage, https://github.com/acie-io/ackc
Project-URL: Repository, https://github.com/acie-io/ackc.git
Project-URL: Documentation, https://github.com/acie-io/ackc#readme
Project-URL: Issues, https://github.com/acie-io/ackc/issues
Project-URL: Release Notes, https://github.com/acie-io/ackc/releases
Author-email: Phillip Sitbon <phillip.sitbon@gmail.com>
License-Expression: Apache-2.0
License-File: license.md
Keywords: access management,api,authentication,authorization,client,enterprise authentication,identity,identity provider,jwt,keycloak,oauth2,openid connect,rbac,security,single sign-on,sso
Classifier: Development Status :: 4 - Beta
Classifier: Environment :: Web Environment
Classifier: Intended Audience :: Developers
Classifier: License :: OSI Approved :: Apache Software License
Classifier: Natural Language :: English
Classifier: Operating System :: OS Independent
Classifier: Programming Language :: Python :: 3 :: Only
Classifier: Programming Language :: Python :: 3.13
Classifier: Programming Language :: Python :: Implementation :: CPython
Classifier: Topic :: Internet
Classifier: Topic :: Internet :: WWW/HTTP
Classifier: Topic :: Software Development :: Libraries
Classifier: Topic :: Software Development :: Libraries :: Application Frameworks
Classifier: Topic :: Software Development :: Libraries :: Python Modules
Requires-Python: >=3.13
Requires-Dist: attrs>=25.3.0
Requires-Dist: niquests>=3.14.1
